LICENSE
README.md
setup.cfg
setup.py
ntient/__init__.py
ntient/api.py
ntient/base.py
ntient/deployment.py
ntient/model.py
ntient/packager.py
ntient/user.py
ntient.egg-info/PKG-INFO
ntient.egg-info/SOURCES.txt
ntient.egg-info/dependency_links.txt
ntient.egg-info/requires.txt
ntient.egg-info/top_level.txt