Metadata-Version: 2.1
Name: ntient
Version: 0.2.0
Summary: Ntient Client Library
Home-page: https://github.com/ntient/ntient
Author: Joel Davenport
Author-email: joel.davenport@ntient.ai
License: MIT
Platform: UNKNOWN
Classifier: Programming Language :: Python :: 3
Classifier: License :: OSI Approved :: MIT License
Classifier: Operating System :: OS Independent
Requires-Python: >=3.6
License-File: LICENSE
